openadp/__init__.py
openadp/client.py
openadp/crypto.py
openadp/keygen.py
openadp/ocrypt.py
openadp-1.0.0.dist-info/METADATA
openadp-1.0.0.dist-info/WHEEL
openadp-1.0.0.dist-info/entry_points.txt
openadp-1.0.0.dist-info/top_level.txt
openadp-1.0.0.dist-info/RECORD
